{
    "title": "Eflak Seferi",
    "video": "data/videos/eflakSeferi.mp4",
    "image": "data/images/eflakSeferi.png",
    "details": [
        "1462",
        "Eflak'ın Osmanlı'ya vergi ödememesi, Macar desteğiyle Osmanlı'ya saldırıya geçmesi ve Osmanlı elçilerinin öldürülmesi.",
        "Eflak seferiyle bölge yeniden Osmanlı'ya bağlandı. Eflak'ta Osmanlı hâkimiyeti yeniden kuruldu."
    ],
    "description": "Eflak Krallığı, uzun süredir Osmanlı'ya ödemesi gereken vergileri ödememekteydi. Ayrıca Macarların desteğini alarak Osmanlı'ya saldırıya geçmiş ve Osmanlı elçilerini öldürmüştür. Bu gelişmeler üzerine Fatih Sultan Mehmet 1462 yılında sefere çıkarak Eflak'ı yeniden Osmanlı topraklarına bağlamıştır."
}